{"contributors": null, "truncated": false, "text": "Gibt es vom Song der Isis ne mp3", "is_quote_status": false, "in_reply_to_status_id": null, "id": 669271675918241792, "favorite_count": 0, "source": "<a href=\"http://twitter.com/download/iphone\" rel=\"nofollow\">Twitter for iPhone</a>", "retweeted": false, "coordinates": null, "entities": {"symbols": [], "user_mentions": [], "hashtags": [], "urls": []}, "in_reply_to_screen_name": null, "in_reply_to_user_id": null, "retweet_count": 0, "id_str": "669271675918241792", "favorited": false, "user": {"follow_request_sent": false, "has_extended_profile": true, "profile_use_background_image": false, "default_profile_image": false, "id": 1591453814, "profile_background_image_url_https": "https://abs.twimg.com/images/themes/theme1/bg.png", "verified": false, "profile_text_color": "000000", "profile_image_url_https": "https://pbs.twimg.com/profile_images/666722711012556800/jporkeVs_normal.jpg", "profile_sidebar_fill_color": "000000", "entities": {"url": {"urls": [{"url": "http://t.co/NxMyCCZajh", "indices": [0, 22], "expanded_url": "http://www.PersonalRennente.com", "display_url": "PersonalRennente.com"}]}, "description": {"urls": []}}, "followers_count": 124, "profile_sidebar_border_color": "000000", "id_str": "1591453814", "profile_background_color": "000000", "listed_count": 4, "is_translation_enabled": false, "utc_offset": 3600, "statuses_count": 11079, "description": "Ich liebe Anzu mehr als Maki", "friends_count": 118, "location": "Alabasta|Grandline", "profile_link_color": "F5ABB5", "profile_image_url": "http://pbs.twimg.com/profile_images/666722711012556800/jporkeVs_normal.jpg", "following": false, "geo_enabled": true, "profile_banner_url": "https://pbs.twimg.com/profile_banners/1591453814/1438725073", "profile_background_image_url": "http://abs.twimg.com/images/themes/theme1/bg.png", "screen_name": "Mongokyou", "lang": "de", "profile_background_tile": false, "favourites_count": 788, "name": "Mongokyou", "notifications": false, "url": "http://t.co/NxMyCCZajh", "created_at": "Sat Jul 13 17:18:16 +0000 2013", "contributors_enabled": false, "time_zone": "Ljubljana", "protected": false, "default_profile": false, "is_translator": false}, "geo": null, "in_reply_to_user_id_str": null, "lang": "de", "created_at": "Tue Nov 24 21:49:36 +0000 2015", "in_reply_to_status_id_str": null, "place": null, "metadata": {"iso_language_code": "de", "result_type": "recent"}}