{"contributors": null, "truncated": false, "text": "Paris attacks may end Europe's open borders https://t.co/4nsw8L5bCc | https://t.co/p5JYdZkamX https://t.co/2XMCRK5D6M", "is_quote_status": false, "in_reply_to_status_id": null, "id": 667853646562922496, "favorite_count": 0, "source": "<a href=\"http://twibble.io\" rel=\"nofollow\">Twibble.io</a>", "retweeted": false, "coordinates": null, "entities": {"symbols": [], "user_mentions": [], "hashtags": [], "urls": [{"url": "https://t.co/4nsw8L5bCc", "indices": [44, 67], "expanded_url": "http://twib.in/l/Rrnkgzyxxae", "display_url": "twib.in/l/Rrnkgzyxxae"}, {"url": "https://t.co/p5JYdZkamX", "indices": [70, 93], "expanded_url": "https://twibble.io", "display_url": "twibble.io"}], "media": [{"expanded_url": "http://twitter.com/jnr_martins/status/667853646562922496/photo/1", "display_url": "pic.twitter.com/2XMCRK5D6M", "url": "https://t.co/2XMCRK5D6M", "media_url_https": "https://pbs.twimg.com/media/CUSxWhxUEAAoDBc.jpg", "id_str": "667853645338120192", "sizes": {"large": {"h": 535, "resize": "fit", "w": 1024}, "small": {"h": 177, "resize": "fit", "w": 340}, "medium": {"h": 313, "resize": "fit", "w": 600}, "thumb": {"h": 150, "resize": "crop", "w": 150}}, "indices": [94, 117], "type": "photo", "id": 667853645338120192, "media_url": "http://pbs.twimg.com/media/CUSxWhxUEAAoDBc.jpg"}]}, "in_reply_to_screen_name": null, "in_reply_to_user_id": null, "retweet_count": 0, "id_str": "667853646562922496", "favorited": false, "user": {"follow_request_sent": false, "has_extended_profile": false, "profile_use_background_image": true, "default_profile_image": false, "id": 709102724, "profile_background_image_url_https": "https://abs.twimg.com/images/themes/theme1/bg.png", "verified": false, "profile_text_color": "333333", "profile_image_url_https": "https://pbs.twimg.com/profile_images/378800000374543082/a63c15e0480c739048de38748004fc16_normal.jpeg", "profile_sidebar_fill_color": "DDEEF6", "entities": {"url": {"urls": [{"url": "http://t.co/pa5jYwVwtE", "indices": [0, 22], "expanded_url": "http://instagram.com/russian__jm", "display_url": "instagram.com/russian__jm"}]}, "description": {"urls": []}}, "followers_count": 1739, "profile_sidebar_border_color": "C0DEED", "id_str": "709102724", "profile_background_color": "C0DEED", "listed_count": 13, "is_translation_enabled": false, "utc_offset": 10800, "statuses_count": 12445, "description": "Info geek|Art Lover|athlete|Extrovert|Photography lover|Hood 1960|Team July|Gooner 4 Life|Freak*IDGAF; Ha! Ha!\nIG: @russian__jm\n#TeamFollowback\n#IamThinking", "friends_count": 1989, "location": "Nairobi", "profile_link_color": "0084B4", "profile_image_url": "http://pbs.twimg.com/profile_images/378800000374543082/a63c15e0480c739048de38748004fc16_normal.jpeg", "following": false, "geo_enabled": true, "profile_banner_url": "https://pbs.twimg.com/profile_banners/709102724/1420554294", "profile_background_image_url": "http://abs.twimg.com/images/themes/theme1/bg.png", "screen_name": "jnr_martins", "lang": "en", "profile_background_tile": false, "favourites_count": 443, "name": "Russian254", "notifications": false, "url": "http://t.co/pa5jYwVwtE", "created_at": "Sat Jul 21 14:57:24 +0000 2012", "contributors_enabled": false, "time_zone": "Baghdad", "protected": false, "default_profile": true, "is_translator": false}, "geo": null, "in_reply_to_user_id_str": null, "possibly_sensitive": false, "lang": "en", "created_at": "Fri Nov 20 23:54:52 +0000 2015", "in_reply_to_status_id_str": null, "place": null, "metadata": {"iso_language_code": "en", "result_type": "recent"}}