{"contributors": null, "truncated": false, "text": "RT @SputnikInt: Got something to hide? #Turkey shows its priorities by downing #Su24 \nhttps://t.co/9LQh7TdVQs #BackStabbed #Syria https://t…", "is_quote_status": false, "in_reply_to_status_id": null, "id": 669660183732334593, "favorite_count": 0, "source": "<a href=\"http://twitter.com/download/android\" rel=\"nofollow\">Twitter for Android</a>", "retweeted": false, "coordinates": null, "entities": {"symbols": [], "user_mentions": [{"id": 34262462, "indices": [3, 14], "id_str": "34262462", "screen_name": "SputnikInt", "name": "Sputnik"}], "hashtags": [{"indices": [39, 46], "text": "Turkey"}, {"indices": [79, 84], "text": "Su24"}, {"indices": [110, 122], "text": "BackStabbed"}, {"indices": [123, 129], "text": "Syria"}], "urls": [{"url": "https://t.co/9LQh7TdVQs", "indices": [86, 109], "expanded_url": "http://sptnkne.ws/ahnF", "display_url": "sptnkne.ws/ahnF"}], "media": [{"source_user_id": 34262462, "source_status_id_str": "669646782826045440", "expanded_url": "http://twitter.com/SputnikInt/status/669646782826045440/photo/1", "display_url": "pic.twitter.com/XSMvszsCsl", "url": "https://t.co/XSMvszsCsl", "media_url_https": "https://pbs.twimg.com/media/CUsNS-OW4AEebut.png", "source_user_id_str": "34262462", "source_status_id": 669646782826045440, "id_str": "669643589186674689", "sizes": {"large": {"h": 732, "resize": "fit", "w": 1024}, "small": {"h": 243, "resize": "fit", "w": 340}, "medium": {"h": 429, "resize": "fit", "w": 600}, "thumb": {"h": 150, "resize": "crop", "w": 150}}, "indices": [139, 140], "type": "photo", "id": 669643589186674689, "media_url": "http://pbs.twimg.com/media/CUsNS-OW4AEebut.png"}]}, "in_reply_to_screen_name": null, "in_reply_to_user_id": null, "retweet_count": 92, "id_str": "669660183732334593", "favorited": false, "retweeted_status": {"contributors": null, "truncated": false, "text": "Got something to hide? #Turkey shows its priorities by downing #Su24 \nhttps://t.co/9LQh7TdVQs #BackStabbed #Syria https://t.co/XSMvszsCsl", "is_quote_status": false, "in_reply_to_status_id": null, "id": 669646782826045440, "favorite_count": 55, "source": "<a href=\"https://about.twitter.com/products/tweetdeck\" rel=\"nofollow\">TweetDeck</a>", "retweeted": false, "coordinates": null, "entities": {"symbols": [], "user_mentions": [], "hashtags": [{"indices": [23, 30], "text": "Turkey"}, {"indices": [63, 68], "text": "Su24"}, {"indices": [94, 106], "text": "BackStabbed"}, {"indices": [107, 113], "text": "Syria"}], "urls": [{"url": "https://t.co/9LQh7TdVQs", "indices": [70, 93], "expanded_url": "http://sptnkne.ws/ahnF", "display_url": "sptnkne.ws/ahnF"}], "media": [{"expanded_url": "http://twitter.com/SputnikInt/status/669646782826045440/photo/1", "display_url": "pic.twitter.com/XSMvszsCsl", "url": "https://t.co/XSMvszsCsl", "media_url_https": "https://pbs.twimg.com/media/CUsNS-OW4AEebut.png", "id_str": "669643589186674689", "sizes": {"large": {"h": 732, "resize": "fit", "w": 1024}, "small": {"h": 243, "resize": "fit", "w": 340}, "medium": {"h": 429, "resize": "fit", "w": 600}, "thumb": {"h": 150, "resize": "crop", "w": 150}}, "indices": [114, 137], "type": "photo", "id": 669643589186674689, "media_url": "http://pbs.twimg.com/media/CUsNS-OW4AEebut.png"}]}, "in_reply_to_screen_name": null, "in_reply_to_user_id": null, "retweet_count": 92, "id_str": "669646782826045440", "favorited": false, "user": {"follow_request_sent": false, "has_extended_profile": false, "profile_use_background_image": false, "default_profile_image": false, "id": 34262462, "profile_background_image_url_https": "https://pbs.twimg.com/profile_background_images/449543599537913856/nNcxAMM_.jpeg", "verified": true, "profile_text_color": "333333", "profile_image_url_https": "https://pbs.twimg.com/profile_images/666179739602853897/ErSGz8e7_normal.png", "profile_sidebar_fill_color": "056EAB", "entities": {"url": {"urls": [{"url": "http://t.co/jG5fV8dLJ2", "indices": [0, 22], "expanded_url": "http://sputniknews.com/", "display_url": "sputniknews.com"}]}, "description": {"urls": []}}, "followers_count": 100749, "profile_sidebar_border_color": "FFFFFF", "id_str": "34262462", "profile_background_color": "000000", "listed_count": 3542, "is_translation_enabled": false, "utc_offset": -18000, "statuses_count": 107463, "description": "Sputnik News Agency and Radio", "friends_count": 184, "location": "", "profile_link_color": "FF9600", "profile_image_url": "http://pbs.twimg.com/profile_images/666179739602853897/ErSGz8e7_normal.png", "following": false, "geo_enabled": false, "profile_banner_url": "https://pbs.twimg.com/profile_banners/34262462/1447664614", "profile_background_image_url": "http://pbs.twimg.com/profile_background_images/449543599537913856/nNcxAMM_.jpeg", "screen_name": "SputnikInt", "lang": "en", "profile_background_tile": true, "favourites_count": 8, "name": "Sputnik", "notifications": false, "url": "http://t.co/jG5fV8dLJ2", "created_at": "Wed Apr 22 12:55:28 +0000 2009", "contributors_enabled": false, "time_zone": "Eastern Time (US & Canada)", "protected": false, "default_profile": false, "is_translator": false}, "geo": null, "in_reply_to_user_id_str": null, "possibly_sensitive": false, "lang": "en", "created_at": "Wed Nov 25 22:40:09 +0000 2015", "in_reply_to_status_id_str": null, "place": null, "metadata": {"iso_language_code": "en", "result_type": "recent"}}, "user": {"follow_request_sent": false, "has_extended_profile": false, "profile_use_background_image": false, "default_profile_image": false, "id": 339569464, "profile_background_image_url_https": "https://abs.twimg.com/images/themes/theme1/bg.png", "verified": false, "profile_text_color": "000000", "profile_image_url_https": "https://pbs.twimg.com/profile_images/584710221664100352/5hi8atMp_normal.jpg", "profile_sidebar_fill_color": "000000", "entities": {"description": {"urls": []}}, "followers_count": 501, "profile_sidebar_border_color": "000000", "id_str": "339569464", "profile_background_color": "000000", "listed_count": 5, "is_translation_enabled": false, "utc_offset": 3600, "statuses_count": 8979, "description": "AKJV Bible believing sinner saved by the grace of Almighty God through the substitutionary blood sacrifice of the sinless Lamb of God, My Lord Jesus Christ", "friends_count": 1179, "location": "~ Wien ~", "profile_link_color": "6A332C", "profile_image_url": "http://pbs.twimg.com/profile_images/584710221664100352/5hi8atMp_normal.jpg", "following": false, "geo_enabled": true, "profile_banner_url": "https://pbs.twimg.com/profile_banners/339569464/1353360470", "profile_background_image_url": "http://abs.twimg.com/images/themes/theme1/bg.png", "screen_name": "lugojiano", "lang": "en", "profile_background_tile": false, "favourites_count": 1350, "name": "1lugojian", "notifications": false, "url": null, "created_at": "Thu Jul 21 09:30:11 +0000 2011", "contributors_enabled": false, "time_zone": "Vienna", "protected": false, "default_profile": false, "is_translator": false}, "geo": null, "in_reply_to_user_id_str": null, "possibly_sensitive": false, "lang": "en", "created_at": "Wed Nov 25 23:33:24 +0000 2015", "in_reply_to_status_id_str": null, "place": null, "metadata": {"iso_language_code": "en", "result_type": "recent"}}