{"contributors": null, "truncated": false, "text": "@UweSchummer Das Gute in den Jahren ist NICHT #Merkel zu verdanken #CDU sollte jetzt nach Syrien migrieren um noch bessere Jahre zu erleben", "is_quote_status": false, "in_reply_to_status_id": 668890867671896064, "id": 668916435536748544, "favorite_count": 0, "source": "<a href=\"http://twitter.com\" rel=\"nofollow\">Twitter Web Client</a>", "retweeted": false, "coordinates": null, "entities": {"symbols": [], "user_mentions": [{"id": 409203792, "indices": [0, 12], "id_str": "409203792", "screen_name": "UweSchummer", "name": "Uwe Schummer"}], "hashtags": [{"indices": [46, 53], "text": "Merkel"}, {"indices": [67, 71], "text": "CDU"}], "urls": []}, "in_reply_to_screen_name": "UweSchummer", "in_reply_to_user_id": 409203792, "retweet_count": 0, "id_str": "668916435536748544", "favorited": false, "user": {"follow_request_sent": false, "has_extended_profile": false, "profile_use_background_image": false, "default_profile_image": true, "id": 4182164968, "profile_background_image_url_https": "https://abs.twimg.com/images/themes/theme1/bg.png", "verified": false, "profile_text_color": "000000", "profile_image_url_https": "https://abs.twimg.com/sticky/default_profile_images/default_profile_2_normal.png", "profile_sidebar_fill_color": "000000", "entities": {"description": {"urls": []}}, "followers_count": 4, "profile_sidebar_border_color": "000000", "id_str": "4182164968", "profile_background_color": "000000", "listed_count": 1, "is_translation_enabled": false, "utc_offset": null, "statuses_count": 62, "description": "", "friends_count": 4, "location": "", "profile_link_color": "89C9FA", "profile_image_url": "http://abs.twimg.com/sticky/default_profile_images/default_profile_2_normal.png", "following": false, "geo_enabled": false, "profile_background_image_url": "http://abs.twimg.com/images/themes/theme1/bg.png", "screen_name": "mirror_jay", "lang": "de", "profile_background_tile": false, "favourites_count": 81, "name": "Jay Mirror", "notifications": false, "url": null, "created_at": "Fri Nov 13 23:04:52 +0000 2015", "contributors_enabled": false, "time_zone": null, "protected": false, "default_profile": false, "is_translator": false}, "geo": null, "in_reply_to_user_id_str": "409203792", "lang": "de", "created_at": "Mon Nov 23 22:18:00 +0000 2015", "in_reply_to_status_id_str": "668890867671896064", "place": null, "metadata": {"iso_language_code": "de", "result_type": "recent"}}