{"contributors": null, "truncated": false, "text": "#parisattacks.#hollande,#syrien,bombenkrieg,#ISIS, der maulheld von paris hat sich beim zeuseln die finger verbrannt https://t.co/DY3YAgRqyr", "is_quote_status": false, "in_reply_to_status_id": null, "id": 668907334865985538, "favorite_count": 0, "source": "<a href=\"http://twitter.com\" rel=\"nofollow\">Twitter Web Client</a>", "retweeted": false, "coordinates": null, "entities": {"symbols": [], "user_mentions": [], "hashtags": [{"indices": [0, 13], "text": "parisattacks"}, {"indices": [14, 23], "text": "hollande"}, {"indices": [24, 31], "text": "syrien"}, {"indices": [44, 49], "text": "ISIS"}], "urls": [], "media": [{"expanded_url": "http://twitter.com/schweizbrennt/status/668907334865985538/photo/1", "display_url": "pic.twitter.com/DY3YAgRqyr", "url": "https://t.co/DY3YAgRqyr", "media_url_https": "https://pbs.twimg.com/media/CUhvrPlWoAEsYCh.png", "id_str": "668907333372780545", "sizes": {"small": {"h": 138, "resize": "fit", "w": 340}, "large": {"h": 349, "resize": "fit", "w": 854}, "medium": {"h": 245, "resize": "fit", "w": 600}, "thumb": {"h": 150, "resize": "crop", "w": 150}}, "indices": [117, 140], "type": "photo", "id": 668907333372780545, "media_url": "http://pbs.twimg.com/media/CUhvrPlWoAEsYCh.png"}]}, "in_reply_to_screen_name": null, "in_reply_to_user_id": null, "retweet_count": 1, "id_str": "668907334865985538", "favorited": false, "user": {"follow_request_sent": false, "has_extended_profile": false, "profile_use_background_image": true, "default_profile_image": false, "id": 3179893455, "profile_background_image_url_https": "https://abs.twimg.com/images/themes/theme1/bg.png", "verified": false, "profile_text_color": "333333", "profile_image_url_https": "https://pbs.twimg.com/profile_images/589922516484890624/RlklzDRf_normal.jpg", "profile_sidebar_fill_color": "DDEEF6", "entities": {"url": {"urls": [{"url": "https://t.co/WWcU95wvTq", "indices": [0, 23], "expanded_url": "http://www.fuckobamamerkelhollande.com", "display_url": "fuckobamamerkelhollande.com"}]}, "description": {"urls": []}}, "followers_count": 75, "profile_sidebar_border_color": "C0DEED", "id_str": "3179893455", "profile_background_color": "C0DEED", "listed_count": 13, "is_translation_enabled": false, "utc_offset": -28800, "statuses_count": 323, "description": "radikal-alternativ. und die härteste satire der schweiz", "friends_count": 59, "location": "zürich, schweiz", "profile_link_color": "0084B4", "profile_image_url": "http://pbs.twimg.com/profile_images/589922516484890624/RlklzDRf_normal.jpg", "following": false, "geo_enabled": false, "profile_banner_url": "https://pbs.twimg.com/profile_banners/3179893455/1447975412", "profile_background_image_url": "http://abs.twimg.com/images/themes/theme1/bg.png", "screen_name": "schweizbrennt", "lang": "de", "profile_background_tile": false, "favourites_count": 2, "name": "schweizbrennt", "notifications": false, "url": "https://t.co/WWcU95wvTq", "created_at": "Sat Apr 18 16:34:56 +0000 2015", "contributors_enabled": false, "time_zone": "Pacific Time (US & Canada)", "protected": false, "default_profile": true, "is_translator": false}, "geo": null, "in_reply_to_user_id_str": null, "possibly_sensitive": false, "lang": "de", "created_at": "Mon Nov 23 21:41:50 +0000 2015", "in_reply_to_status_id_str": null, "place": null, "metadata": {"iso_language_code": "de", "result_type": "recent"}}