{"contributors": null, "truncated": false, "text": "RT @DavidBobin: Marc Trévidic : \"Il y a autant d'individus à surveiller que d'agents de la DGSI !\" https://t.co/LpgCViOAeO via @lobs", "is_quote_status": false, "in_reply_to_status_id": null, "id": 668555190975471616, "favorite_count": 0, "source": "<a href=\"http://twitter.com/download/iphone\" rel=\"nofollow\">Twitter for iPhone</a>", "retweeted": false, "coordinates": null, "entities": {"symbols": [], "user_mentions": [{"id": 2308595995, "indices": [3, 14], "id_str": "2308595995", "screen_name": "DavidBobin", "name": "David Bobin"}, {"id": 21313364, "indices": [127, 132], "id_str": "21313364", "screen_name": "lobs", "name": "L'Obs"}], "hashtags": [], "urls": [{"url": "https://t.co/LpgCViOAeO", "indices": [99, 122], "expanded_url": "http://tempsreel.nouvelobs.com/attentats-terroristes-a-paris/20151115.OBS9552/marc-trevidic-il-y-a-autant-d-individus-a-surveiller-que-d-agents-de-la-dgsi.html", "display_url": "tempsreel.nouvelobs.com/attentats-terr…"}]}, "in_reply_to_screen_name": null, "in_reply_to_user_id": null, "retweet_count": 4, "id_str": "668555190975471616", "favorited": false, "retweeted_status": {"contributors": null, "truncated": false, "text": "Marc Trévidic : \"Il y a autant d'individus à surveiller que d'agents de la DGSI !\" https://t.co/LpgCViOAeO via @lobs", "is_quote_status": false, "in_reply_to_status_id": null, "id": 668554929234161664, "favorite_count": 3, "source": "<a href=\"http://twitter.com\" rel=\"nofollow\">Twitter Web Client</a>", "retweeted": false, "coordinates": null, "entities": {"symbols": [], "user_mentions": [{"id": 21313364, "indices": [111, 116], "id_str": "21313364", "screen_name": "lobs", "name": "L'Obs"}], "hashtags": [], "urls": [{"url": "https://t.co/LpgCViOAeO", "indices": [83, 106], "expanded_url": "http://tempsreel.nouvelobs.com/attentats-terroristes-a-paris/20151115.OBS9552/marc-trevidic-il-y-a-autant-d-individus-a-surveiller-que-d-agents-de-la-dgsi.html", "display_url": "tempsreel.nouvelobs.com/attentats-terr…"}]}, "in_reply_to_screen_name": null, "in_reply_to_user_id": null, "retweet_count": 4, "id_str": "668554929234161664", "favorited": false, "user": {"follow_request_sent": false, "has_extended_profile": false, "profile_use_background_image": false, "default_profile_image": false, "id": 2308595995, "profile_background_image_url_https": "https://abs.twimg.com/images/themes/theme9/bg.gif", "verified": false, "profile_text_color": "000000", "profile_image_url_https": "https://pbs.twimg.com/profile_images/667983587711565824/gRhv1Kj6_normal.jpg", "profile_sidebar_fill_color": "000000", "entities": {"description": {"urls": []}}, "followers_count": 1976, "profile_sidebar_border_color": "000000", "id_str": "2308595995", "profile_background_color": "000000", "listed_count": 88, "is_translation_enabled": false, "utc_offset": -28800, "statuses_count": 39621, "description": "Filmmaker director & Video journalist. #TF1 #M6 #TMC #D8 #Planete+ #F2 #F3 #AFPTV #BFMTV #Radiocanada.", "friends_count": 2782, "location": "France", "profile_link_color": "ABB8C2", "profile_image_url": "http://pbs.twimg.com/profile_images/667983587711565824/gRhv1Kj6_normal.jpg", "following": false, "geo_enabled": true, "profile_banner_url": "https://pbs.twimg.com/profile_banners/2308595995/1447485801", "profile_background_image_url": "http://abs.twimg.com/images/themes/theme9/bg.gif", "screen_name": "DavidBobin", "lang": "fr", "profile_background_tile": false, "favourites_count": 8494, "name": "David Bobin", "notifications": false, "url": null, "created_at": "Fri Jan 24 16:08:45 +0000 2014", "contributors_enabled": false, "time_zone": "Pacific Time (US & Canada)", "protected": false, "default_profile": false, "is_translator": false}, "geo": null, "in_reply_to_user_id_str": null, "possibly_sensitive": false, "lang": "fr", "created_at": "Sun Nov 22 22:21:30 +0000 2015", "in_reply_to_status_id_str": null, "place": null, "metadata": {"iso_language_code": "fr", "result_type": "recent"}}, "user": {"follow_request_sent": false, "has_extended_profile": false, "profile_use_background_image": true, "default_profile_image": false, "id": 520699439, "profile_background_image_url_https": "https://pbs.twimg.com/profile_background_images/378800000159045376/jX1NmTpd.jpeg", "verified": false, "profile_text_color": "333333", "profile_image_url_https": "https://pbs.twimg.com/profile_images/639526802977869824/Qov_6C7s_normal.jpg", "profile_sidebar_fill_color": "DDEEF6", "entities": {"description": {"urls": []}}, "followers_count": 82, "profile_sidebar_border_color": "FFFFFF", "id_str": "520699439", "profile_background_color": "C0DEED", "listed_count": 1, "is_translation_enabled": false, "utc_offset": 3600, "statuses_count": 690, "description": "Le lion reste lion même dépourvu de ses griffes et le chien reste chien même élevé au milieu des lions", "friends_count": 549, "location": "Paris", "profile_link_color": "0084B4", "profile_image_url": "http://pbs.twimg.com/profile_images/639526802977869824/Qov_6C7s_normal.jpg", "following": false, "geo_enabled": true, "profile_banner_url": "https://pbs.twimg.com/profile_banners/520699439/1385825815", "profile_background_image_url": "http://pbs.twimg.com/profile_background_images/378800000159045376/jX1NmTpd.jpeg", "screen_name": "vussad", "lang": "en-gb", "profile_background_tile": true, "favourites_count": 737, "name": "Boussad Allouane", "notifications": false, "url": null, "created_at": "Sat Mar 10 20:13:20 +0000 2012", "contributors_enabled": false, "time_zone": "Amsterdam", "protected": false, "default_profile": false, "is_translator": false}, "geo": null, "in_reply_to_user_id_str": null, "possibly_sensitive": false, "lang": "fr", "created_at": "Sun Nov 22 22:22:33 +0000 2015", "in_reply_to_status_id_str": null, "place": null, "metadata": {"iso_language_code": "fr", "result_type": "recent"}}