{"contributors": null, "truncated": false, "text": "RT @pradeeplovesall: @vayakkattil @Ajit_Doval @ravi_sec After Paris and other attacks it is wake up call for all of us globally.", "is_quote_status": false, "in_reply_to_status_id": null, "id": 668578107134087168, "favorite_count": 0, "source": "<a href=\"http://twitter.com/download/android\" rel=\"nofollow\">Twitter for Android</a>", "retweeted": false, "coordinates": null, "entities": {"symbols": [], "user_mentions": [{"id": 323064545, "indices": [3, 19], "id_str": "323064545", "screen_name": "pradeeplovesall", "name": "Pradeep Chowdhary"}, {"id": 76944852, "indices": [21, 33], "id_str": "76944852", "screen_name": "vayakkattil", "name": "Bhojarajan"}, {"id": 2572315144, "indices": [34, 45], "id_str": "2572315144", "screen_name": "Ajit_Doval", "name": "#Ajit Doval"}, {"id": 105771045, "indices": [46, 55], "id_str": "105771045", "screen_name": "ravi_sec", "name": "Ravi Kiren"}], "hashtags": [], "urls": []}, "in_reply_to_screen_name": null, "in_reply_to_user_id": null, "retweet_count": 1, "id_str": "668578107134087168", "favorited": false, "retweeted_status": {"contributors": null, "truncated": false, "text": "@vayakkattil @Ajit_Doval @ravi_sec After Paris and other attacks it is wake up call for all of us globally.", "is_quote_status": false, "in_reply_to_status_id": 668488314194792448, "id": 668492335462813697, "favorite_count": 2, "source": "<a href=\"http://twitter.com/download/android\" rel=\"nofollow\">Twitter for Android</a>", "retweeted": false, "coordinates": null, "entities": {"symbols": [], "user_mentions": [{"id": 76944852, "indices": [0, 12], "id_str": "76944852", "screen_name": "vayakkattil", "name": "Bhojarajan"}, {"id": 2572315144, "indices": [13, 24], "id_str": "2572315144", "screen_name": "Ajit_Doval", "name": "#Ajit Doval"}, {"id": 105771045, "indices": [25, 34], "id_str": "105771045", "screen_name": "ravi_sec", "name": "Ravi Kiren"}], "hashtags": [], "urls": []}, "in_reply_to_screen_name": "pradeeplovesall", "in_reply_to_user_id": 323064545, "retweet_count": 1, "id_str": "668492335462813697", "favorited": false, "user": {"follow_request_sent": false, "has_extended_profile": false, "profile_use_background_image": true, "default_profile_image": false, "id": 323064545, "profile_background_image_url_https": "https://abs.twimg.com/images/themes/theme1/bg.png", "verified": false, "profile_text_color": "333333", "profile_image_url_https": "https://pbs.twimg.com/profile_images/561538383709601792/1JU5LtK5_normal.jpeg", "profile_sidebar_fill_color": "DDEEF6", "entities": {"url": {"urls": [{"url": "http://t.co/c41YFxXiiJ", "indices": [0, 22], "expanded_url": "http://www.Icdi.co", "display_url": "Icdi.co"}]}, "description": {"urls": []}}, "followers_count": 929, "profile_sidebar_border_color": "FFFFFF", "id_str": "323064545", "profile_background_color": "C0DEED", "listed_count": 36, "is_translation_enabled": false, "utc_offset": 19800, "statuses_count": 18983, "description": "I m Security Expert and work with leading Foreign Security co's on various security projects,training & implementation.Also advise many State,Central Police etc", "friends_count": 2214, "location": "New Delhi,Hyderabad,Bangalore", "profile_link_color": "0084B4", "profile_image_url": "http://pbs.twimg.com/profile_images/561538383709601792/1JU5LtK5_normal.jpeg", "following": false, "geo_enabled": true, "profile_banner_url": "https://pbs.twimg.com/profile_banners/323064545/1379865936", "profile_background_image_url": "http://abs.twimg.com/images/themes/theme1/bg.png", "screen_name": "pradeeplovesall", "lang": "en", "profile_background_tile": false, "favourites_count": 184, "name": "Pradeep Chowdhary", "notifications": false, "url": "http://t.co/c41YFxXiiJ", "created_at": "Fri Jun 24 05:51:42 +0000 2011", "contributors_enabled": false, "time_zone": "New Delhi", "protected": false, "default_profile": false, "is_translator": false}, "geo": null, "in_reply_to_user_id_str": "323064545", "lang": "en", "created_at": "Sun Nov 22 18:12:47 +0000 2015", "in_reply_to_status_id_str": "668488314194792448", "place": null, "metadata": {"iso_language_code": "en", "result_type": "recent"}}, "user": {"follow_request_sent": false, "has_extended_profile": false, "profile_use_background_image": true, "default_profile_image": false, "id": 2496647126, "profile_background_image_url_https": "https://abs.twimg.com/images/themes/theme1/bg.png", "verified": false, "profile_text_color": "333333", "profile_image_url_https": "https://pbs.twimg.com/profile_images/489333231846559744/hiJP2LgW_normal.jpeg", "profile_sidebar_fill_color": "DDEEF6", "entities": {"description": {"urls": []}}, "followers_count": 1917, "profile_sidebar_border_color": "FFFFFF", "id_str": "2496647126", "profile_background_color": "C0DEED", "listed_count": 212, "is_translation_enabled": false, "utc_offset": 19800, "statuses_count": 87650, "description": "A Devotee of Sri Sri @ AOL, Bangalore !!! ... 'Dreaming for ... a Glorious INDIA ... in a Beautiful WORLD' !!! ... RTs are Not  Endorsements !", "friends_count": 2198, "location": "Kanyakumari, INDIA. ", "profile_link_color": "EB6105", "profile_image_url": "http://pbs.twimg.com/profile_images/489333231846559744/hiJP2LgW_normal.jpeg", "following": false, "geo_enabled": false, "profile_banner_url": "https://pbs.twimg.com/profile_banners/2496647126/1405501867", "profile_background_image_url": "http://abs.twimg.com/images/themes/theme1/bg.png", "screen_name": "A31X64Vijay", "lang": "en", "profile_background_tile": false, "favourites_count": 36229, "name": "Vijaya Kumar", "notifications": false, "url": null, "created_at": "Thu May 15 16:06:37 +0000 2014", "contributors_enabled": false, "time_zone": "New Delhi", "protected": false, "default_profile": false, "is_translator": false}, "geo": null, "in_reply_to_user_id_str": null, "lang": "en", "created_at": "Sun Nov 22 23:53:36 +0000 2015", "in_reply_to_status_id_str": null, "place": null, "metadata": {"iso_language_code": "en", "result_type": "recent"}}