{"contributors": null, "truncated": false, "text": "أصبح تويتر ميدان للأخبار المزعجة و المؤلمة ، أما آن للظلام أن ينجلي ؟\n\n#الكويت #سوريا #مصر #العراق #لبنان #تونس #اليمن #ليبيا #داعش", "is_quote_status": false, "in_reply_to_status_id": null, "id": 669261014618218496, "favorite_count": 0, "source": "<a href=\"http://twitter.com/#!/download/ipad\" rel=\"nofollow\">Twitter for iPad</a>", "retweeted": false, "coordinates": null, "entities": {"symbols": [], "user_mentions": [], "hashtags": [{"indices": [71, 78], "text": "الكويت"}, {"indices": [79, 85], "text": "سوريا"}, {"indices": [86, 90], "text": "مصر"}, {"indices": [91, 98], "text": "العراق"}, {"indices": [99, 105], "text": "لبنان"}, {"indices": [106, 111], "text": "تونس"}, {"indices": [112, 118], "text": "اليمن"}, {"indices": [119, 125], "text": "ليبيا"}, {"indices": [126, 131], "text": "داعش"}], "urls": []}, "in_reply_to_screen_name": null, "in_reply_to_user_id": null, "retweet_count": 0, "id_str": "669261014618218496", "favorited": false, "user": {"follow_request_sent": false, "has_extended_profile": false, "profile_use_background_image": true, "default_profile_image": false, "id": 244605268, "profile_background_image_url_https": "https://abs.twimg.com/images/themes/theme1/bg.png", "verified": false, "profile_text_color": "333333", "profile_image_url_https": "https://pbs.twimg.com/profile_images/666582610144010240/Jgsxsuyb_normal.jpg", "profile_sidebar_fill_color": "DDEEF6", "entities": {"description": {"urls": []}}, "followers_count": 2547, "profile_sidebar_border_color": "000000", "id_str": "244605268", "profile_background_color": "C0DEED", "listed_count": 8, "is_translation_enabled": false, "utc_offset": 10800, "statuses_count": 851, "description": "........{{ مقدم أخبار و برامج سياسية في قناة المجلس }}....... هنا أمثل نفسي لا جهة عملي", "friends_count": 527, "location": "", "profile_link_color": "0084B4", "profile_image_url": "http://pbs.twimg.com/profile_images/666582610144010240/Jgsxsuyb_normal.jpg", "following": false, "geo_enabled": false, "profile_banner_url": "https://pbs.twimg.com/profile_banners/244605268/1433883747", "profile_background_image_url": "http://abs.twimg.com/images/themes/theme1/bg.png", "screen_name": "AHMAD_ALWAHIDAH", "lang": "ar", "profile_background_tile": false, "favourites_count": 131, "name": "أحمد الوهيدة", "notifications": false, "url": null, "created_at": "Sat Jan 29 18:05:26 +0000 2011", "contributors_enabled": false, "time_zone": "Kuwait", "protected": false, "default_profile": false, "is_translator": false}, "geo": null, "in_reply_to_user_id_str": null, "lang": "ar", "created_at": "Tue Nov 24 21:07:14 +0000 2015", "in_reply_to_status_id_str": null, "place": null, "metadata": {"iso_language_code": "ar", "result_type": "recent"}}